CHANGES.txt
bootstrap.py
buildout.cfg
setup.py
src/z3c/__init__.py
src/z3c.zalchemy.egg-info/PKG-INFO
src/z3c.zalchemy.egg-info/SOURCES.txt
src/z3c.zalchemy.egg-info/dependency_links.txt
src/z3c.zalchemy.egg-info/not-zip-safe
src/z3c.zalchemy.egg-info/requires.txt
src/z3c.zalchemy.egg-info/top_level.txt
src/z3c/zalchemy/README.txt
src/z3c/zalchemy/SETUP.cfg
src/z3c/zalchemy/TODO.txt
src/z3c/zalchemy/__init__.py
src/z3c/zalchemy/configure.zcml
src/z3c/zalchemy/container.py
src/z3c/zalchemy/container.txt
src/z3c/zalchemy/datamanager.py
src/z3c/zalchemy/i18n.py
src/z3c/zalchemy/interfaces.py
src/z3c/zalchemy/meta.zcml
src/z3c/zalchemy/metaconfigure.py
src/z3c/zalchemy/metadirectives.py
src/z3c/zalchemy/z3c.zalchemy-configure.zcml
src/z3c/zalchemy/z3c.zalchemy-meta.zcml
src/z3c/zalchemy/browser/__init__.py
src/z3c/zalchemy/browser/configure.zcml
src/z3c/zalchemy/browser/engine.gif
src/z3c/zalchemy/browser/views.py
src/z3c/zalchemy/demo/README.txt
src/z3c/zalchemy/demo/TODO.txt
src/z3c/zalchemy/demo/__init__.py
src/z3c/zalchemy/demo/z3c.zalchemy.demo-configure.zcml
src/z3c/zalchemy/demo/demo_1/__init__.py
src/z3c/zalchemy/demo/demo_1/configure.zcml
src/z3c/zalchemy/demo/demo_1/container.py
src/z3c/zalchemy/demo/demo_1/interfaces.py
src/z3c/zalchemy/demo/demo_1/message.py
src/z3c/zalchemy/demo/demo_1/browser/__init__.py
src/z3c/zalchemy/demo/demo_1/browser/configure.zcml
src/z3c/zalchemy/demo/demo_1/browser/message.py
src/z3c/zalchemy/demo/demo_1/browser/view.pt
src/z3c/zalchemy/demo/demo_2/__init__.py
src/z3c/zalchemy/demo/demo_2/configure.zcml
src/z3c/zalchemy/demo/demo_2/container.py
src/z3c/zalchemy/demo/demo_2/interfaces.py
src/z3c/zalchemy/demo/demo_2/message.py
src/z3c/zalchemy/demo/demo_2/browser/__init__.py
src/z3c/zalchemy/demo/demo_2/browser/configure.zcml
src/z3c/zalchemy/demo/demo_2/browser/message.py
src/z3c/zalchemy/demo/demo_2/browser/view.pt
src/z3c/zalchemy/demo/demo_3/__init__.py
src/z3c/zalchemy/demo/demo_3/configure.zcml
src/z3c/zalchemy/demo/demo_3/container.py
src/z3c/zalchemy/demo/demo_3/interfaces.py
src/z3c/zalchemy/demo/demo_3/message.py
src/z3c/zalchemy/demo/demo_3/browser/__init__.py
src/z3c/zalchemy/demo/demo_3/browser/configure.zcml
