Metadata-Version: 1.0
Name: z3c.zalchemy
Version: 0.2.2
Summary: SQLAlchemy integration into Zope 3
Home-page: http://pypi.python.org/pypi/z3c.sqlalchemy
Author: Juergen Kartnaller and the Zope Community
Author-email: zope3-dev@zope.org
License: ZPL 2.1
Platform: UNKNOWN
